{
    "type":"note",
    "title": "0425ハイキュー!!ゴミ捨て場の決戦",
    "artist": "ヨン",
    "audio": "audio/tabun.mp3",
    "lyrics": [
        {
            "japanese":"同室 どうしつ 名詞",
            "chinese":"同房的(人)"
        },
        {
            "japanese":"患者 かんじゃ 名詞",
            "chinese":"病人"
        },
        {
            "japanese":"様子 ようす 名詞",
            "chinese":"情況; 姿態; 樣子"
        },
        {
            "japanese":"そっくり 副詞",
            "chinese":"全部; 完全; 原封不動; 一模一樣"
        },
        {
            "japanese":"負け越す まけこす 動詞",
            "chinese":"負多勝少"
        },
        {
            "japanese":"若き わかき 名詞",
            "chinese":"年輕人"
        },
        {
            "japanese":"闘将 とうしょう 名詞",
            "chinese":"鬥志旺盛的主將(運動員)"
        },
        {
            "japanese":"晴れ舞台 はれぶたい 名詞",
            "chinese":"大勢の前で何かをする名誉な場面"
        },
        {
            "japanese":"オールラウンダー  名詞",
            "chinese":"全能"
        },
        {
            "japanese":"馴染み なじみ 名詞",
            "chinese":"適應(人或環境)而感到親切"
        },
        {
            "japanese":"冷静 れいせい 名詞",
            "chinese":"冷靜; 鎮靜"
        }
    ],
    "notes":[
    ]
}